{"lastUsed":1626401991872,"path":"C:\/Users\/guilh\/Documents\/Cod3r\/Arrays","projectCount":1,"recentFiles":[{"path":"\/exercicios\/src\/arrays","parentWorkspace":"C:\/Users\/guilh\/Documents\/Cod3r\/Arrays","name":"Exercicio.java","lastModified":1620354661670,"locationURI":"file:\/C:\/Users\/guilh\/Documents\/Cod3r\/Arrays\/exercicios\/src\/arrays\/Exercicio.java"},{"path":"\/exercicios\/src\/colecoes","parentWorkspace":"C:\/Users\/guilh\/Documents\/Cod3r\/Arrays","name":"Lista.java","lastModified":1621558469914,"locationURI":"file:\/C:\/Users\/guilh\/Documents\/Cod3r\/Arrays\/exercicios\/src\/colecoes\/Lista.java"},{"path":"\/exercicios\/src\/classe","parentWorkspace":"C:\/Users\/guilh\/Documents\/Cod3r\/Arrays","name":"Usuario.java","lastModified":1620955239524,"locationURI":"file:\/C:\/Users\/guilh\/Documents\/Cod3r\/Arrays\/exercicios\/src\/classe\/Usuario.java"},{"path":"\/exercicios\/src\/classe","parentWorkspace":"C:\/Users\/guilh\/Documents\/Cod3r\/Arrays","name":"Equals.java","lastModified":1621304567677,"locationURI":"file:\/C:\/Users\/guilh\/Documents\/Cod3r\/Arrays\/exercicios\/src\/classe\/Equals.java"},{"path":"\/exercicios\/src\/arrays","parentWorkspace":"C:\/Users\/guilh\/Documents\/Cod3r\/Arrays","name":"Matriz.java","lastModified":1620871551299,"locationURI":"file:\/C:\/Users\/guilh\/Documents\/Cod3r\/Arrays\/exercicios\/src\/arrays\/Matriz.java"},{"path":"\/exercicios\/src\/arrays","parentWorkspace":"C:\/Users\/guilh\/Documents\/Cod3r\/Arrays","name":"DesafioArray.java","lastModified":1621304567677,"locationURI":"file:\/C:\/Users\/guilh\/Documents\/Cod3r\/Arrays\/exercicios\/src\/arrays\/DesafioArray.java"},{"path":"\/exercicios\/src\/colecoes","parentWorkspace":"C:\/Users\/guilh\/Documents\/Cod3r\/Arrays","name":"Fila.java","lastModified":1622080824103,"locationURI":"file:\/C:\/Users\/guilh\/Documents\/Cod3r\/Arrays\/exercicios\/src\/colecoes\/Fila.java"},{"path":"\/exercicios\/src\/arrays","parentWorkspace":"C:\/Users\/guilh\/Documents\/Cod3r\/Arrays","name":"DesafioArray2.java","lastModified":1621304567677,"locationURI":"file:\/C:\/Users\/guilh\/Documents\/Cod3r\/Arrays\/exercicios\/src\/arrays\/DesafioArray2.java"},{"path":"\/exercicios\/src\/colecoes","parentWorkspace":"C:\/Users\/guilh\/Documents\/Cod3r\/Arrays","name":"Usuario.java","lastModified":1621557480758,"locationURI":"file:\/C:\/Users\/guilh\/Documents\/Cod3r\/Arrays\/exercicios\/src\/colecoes\/Usuario.java"},{"path":"\/exercicios\/src\/arrays","parentWorkspace":"C:\/Users\/guilh\/Documents\/Cod3r\/Arrays","name":"ExercicioForeach.java","lastModified":1620355541209,"locationURI":"file:\/C:\/Users\/guilh\/Documents\/Cod3r\/Arrays\/exercicios\/src\/arrays\/ExercicioForeach.java"},{"path":"\/exercicios\/src\/arrays","parentWorkspace":"C:\/Users\/guilh\/Documents\/Cod3r\/Arrays","name":"ExercicioFacul.java","lastModified":1621304567677,"locationURI":"file:\/C:\/Users\/guilh\/Documents\/Cod3r\/Arrays\/exercicios\/src\/arrays\/ExercicioFacul.java"},{"path":"\/exercicios\/src\/colecoes","parentWorkspace":"C:\/Users\/guilh\/Documents\/Cod3r\/Arrays","name":"ConjuntoBaguncado.java","lastModified":1621304567677,"locationURI":"file:\/C:\/Users\/guilh\/Documents\/Cod3r\/Arrays\/exercicios\/src\/colecoes\/ConjuntoBaguncado.java"},{"path":"\/exercicios\/src\/colecoes","parentWorkspace":"C:\/Users\/guilh\/Documents\/Cod3r\/Arrays","name":"ConjuntoComportado.java","lastModified":1621304567677,"locationURI":"file:\/C:\/Users\/guilh\/Documents\/Cod3r\/Arrays\/exercicios\/src\/colecoes\/ConjuntoComportado.java"},{"path":"\/exercicios\/src\/arrays","parentWorkspace":"C:\/Users\/guilh\/Documents\/Cod3r\/Arrays","name":"Foreach.java","lastModified":1620354661690,"locationURI":"file:\/C:\/Users\/guilh\/Documents\/Cod3r\/Arrays\/exercicios\/src\/arrays\/Foreach.java"},{"path":"\/exercicios\/src\/colecoes","parentWorkspace":"C:\/Users\/guilh\/Documents\/Cod3r\/Arrays","name":"Pilha.java","lastModified":1622162468517,"locationURI":"file:\/C:\/Users\/guilh\/Documents\/Cod3r\/Arrays\/exercicios\/src\/colecoes\/Pilha.java"}]}